{
  "seed": 20260227,
  "chow_liu_parent": [
    0,
    2,
    0,
    2,
    5,
    6,
    2
  ],
  "hub_node": 2,
  "hub_edges": [
    [
      0,
      2
    ],
    [
      1,
      2
    ],
    [
      2,
      3
    ],
    [
      2,
      6
    ]
  ],
  "base_rank": 16,
  "key_pairs": [
    [
      0,
      2
    ],
    [
      1,
      2
    ],
    [
      2,
      6
    ],
    [
      5,
      6
    ]
  ],
  "rows": [
    {
      "config": "chain (baseline)",
      "hub_rank": null,
      "ms_step": 5.129237499999917,
      "total_s": 3.4724181660000006,
      "stop_step": 330,
      "val_l2": -0.510572620971829,
      "key_iae": 0.5529687007410079
    },
    {
      "config": "chow_liu hub_rank=16 (baseline=16)",
      "hub_rank": 16,
      "ms_step": 180.3071708500003,
      "total_s": 76.416291875,
      "stop_step": 400,
      "val_l2": -0.9837796371377909,
      "key_iae": 0.26050129229753494
    },
    {
      "config": "chow_liu hub_rank=12",
      "hub_rank": 12,
      "ms_step": 52.091064599999726,
      "total_s": 22.642192499999993,
      "stop_step": 400,
      "val_l2": -0.9583020772842338,
      "key_iae": 0.27378527032587485
    },
    {
      "config": "chow_liu hub_rank=8",
      "hub_rank": 8,
      "ms_step": 15.1692292000007,
      "total_s": 5.416351625000004,
      "stop_step": 270,
      "val_l2": -0.8036971672563383,
      "key_iae": 0.38586639584983107
    },
    {
      "config": "chow_liu hub_rank=4",
      "hub_rank": 4,
      "ms_step": 4.151339599999915,
      "total_s": 2.8653393749999907,
      "stop_step": 400,
      "val_l2": -0.7421978650560206,
      "key_iae": 0.43164895735225745
    },
    {
      "config": "chow_liu hub_rank=2",
      "hub_rank": 2,
      "ms_step": 2.659339599999555,
      "total_s": 2.8147366249999948,
      "stop_step": 400,
      "val_l2": -0.44370493967963964,
      "key_iae": 0.5980312247388153
    }
  ]
}